<board><map><ent><xy><x>5</x><y>5</y></xy><tile><connect><n>0</n><n>7</n></connect><connect><n>1</n><n>2</n></connect><connect><n>3</n><n>5</n></connect><connect><n>4</n><n>6</n></connect></tile></ent><ent><xy><x>0</x><y>5</y></xy><tile><connect><n>0</n><n>1</n></connect><connect><n>2</n><n>7</n></connect><connect><n>3</n><n>6</n></connect><connect><n>4</n><n>5</n></connect></tile></ent><ent><xy><x>5</x><y>0</y></xy><tile><connect><n>0</n><n>3</n></connect><connect><n>1</n><n>6</n></connect><connect><n>2</n><n>4</n></connect><connect><n>5</n><n>7</n></connect></tile></ent><ent><xy><x>0</x><y>0</y></xy><tile><connect><n>0</n><n>3</n></connect><connect><n>1</n><n>6</n></connect><connect><n>2</n><n>5</n></connect><connect><n>4</n><n>7</n></connect></tile></ent></map><map><ent><color>orange</color><pawn-loc><v></v><n>1</n><n>11</n></pawn-loc></ent><ent><color>red</color><pawn-loc><v></v><n>5</n><n>11</n></pawn-loc></ent><ent><color>sienna</color><pawn-loc><v></v><n>0</n><n>5</n></pawn-loc></ent><ent><color>blue</color><pawn-loc><v></v><n>1</n><n>1</n></pawn-loc></ent><ent><color>hotpink</color><pawn-loc><h></h><n>6</n><n>0</n></pawn-loc></ent><ent><color>green</color><pawn-loc><h></h><n>1</n><n>11</n></pawn-loc></ent></map></board>